m1_api_wrapper-3.0.2.dist-info/licenses/LICENSE
m1wrapper/__init__.py
m1wrapper/config.py
m1wrapper/errors.py
m1wrapper/m1wrapper.py
m1wrapper/search.py
m1wrapper/traverse.py
m1_api_wrapper-3.0.2.dist-info/METADATA
m1_api_wrapper-3.0.2.dist-info/WHEEL
m1_api_wrapper-3.0.2.dist-info/top_level.txt
m1_api_wrapper-3.0.2.dist-info/RECORD
